Metadata-Version: 2.1
Name: lbh15
Version: 2.1.0
Summary: Python implementation of liquid metal properties from Handbook on Lead-bismuth Eutectic Alloy and Lead Properties, Materials Compatibility, Thermal-hydraulics and Technologies
Author: Daniele Panico, Daniele Tomatis, Gabriele Ottino
Author-email: Daniele Panico <daniele.panico@newcleo.com>, Daniele Tomatis <daniele.tomatis@newcleo.com>
License: lgpl v3
Classifier: Development Status :: 5 - Production/Stable
Classifier: Intended Audience :: Education
Classifier: Intended Audience :: Science/Research
Classifier: License :: OSI Approved :: GNU Lesser General Public License v3 (LGPLv3)
Classifier: Natural Language :: English
Classifier: Operating System :: OS Independent
Classifier: Programming Language :: Python
Classifier: Topic :: Scientific/Engineering
Classifier: Topic :: Scientific/Engineering :: Physics
Classifier: Topic :: Software Development :: Libraries :: Python Modules
Requires-Python: >=3.8.10
License-File: LICENSE
Requires-Dist: scipy>=1.8.1
Requires-Dist: numpy>=1.22.3
Requires-Dist: sphinx>=6.2.1
Requires-Dist: sphinx-rtd-theme>=1.3.0
Requires-Dist: myst-parser>=1.0.0
Requires-Dist: sphinxcontrib-bibtex>=2.5.0
